<library path="eidos_plugins">
  <class name="eidos::GpsFactor"
         type="eidos::GpsFactor"
         base_class_type="eidos::FactorPlugin">
    <description>GPS factor. Provides BiasedGPSFactor constraints from GNSS data.</description>
  </class>
  <class name="eidos::EuclideanDistanceLoopClosureFactor"
         type="eidos::EuclideanDistanceLoopClosureFactor"
         base_class_type="eidos::FactorPlugin">
    <description>Euclidean distance-based loop closure. Detects loops via KD-tree radius search and validates with ICP alignment.</description>
  </class>
</library>
